main.py
typer_try-0.1.0.dist-info/METADATA
typer_try-0.1.0.dist-info/WHEEL
typer_try-0.1.0.dist-info/entry_points.txt
typer_try-0.1.0.dist-info/top_level.txt
typer_try-0.1.0.dist-info/RECORD
